MANIFEST.in
Readme.md
dev-requirements.frozen.txt
dev-requirements.txt
licence.txt
noxfile.py
requirements.frozen.txt
requirements.txt
setup.cfg
setup.py
pandas_ml_utils_torch/__init__.py
pandas_ml_utils_torch/distribution.py
pandas_ml_utils_torch/layers.py
pandas_ml_utils_torch/merging_cross_folds.py
pandas_ml_utils_torch/pytorch_base.py
pandas_ml_utils_torch/pytorch_model.py
pandas_ml_utils_torch/utils.py
pandas_ml_utils_torch.egg-info/PKG-INFO
pandas_ml_utils_torch.egg-info/SOURCES.txt
pandas_ml_utils_torch.egg-info/dependency_links.txt
pandas_ml_utils_torch.egg-info/requires.txt
pandas_ml_utils_torch.egg-info/top_level.txt
pandas_ml_utils_torch/__pycache__/__init__.cpython-37.pyc
pandas_ml_utils_torch/__pycache__/__init__.cpython-38.pyc
pandas_ml_utils_torch/__pycache__/distribution.cpython-38.pyc
pandas_ml_utils_torch/__pycache__/layers.cpython-37.pyc
pandas_ml_utils_torch/__pycache__/layers.cpython-38.pyc
pandas_ml_utils_torch/__pycache__/merging_cross_folds.cpython-37.pyc
pandas_ml_utils_torch/__pycache__/merging_cross_folds.cpython-38.pyc
pandas_ml_utils_torch/__pycache__/pytorch_base.cpython-37.pyc
pandas_ml_utils_torch/__pycache__/pytorch_base.cpython-38.pyc
pandas_ml_utils_torch/__pycache__/pytorch_model.cpython-37.pyc
pandas_ml_utils_torch/__pycache__/pytorch_model.cpython-38.pyc
pandas_ml_utils_torch/__pycache__/utils.cpython-37.pyc
pandas_ml_utils_torch/__pycache__/utils.cpython-38.pyc
pandas_ml_utils_torch/loss/__init__.py
pandas_ml_utils_torch/loss/_loss_utils.py
pandas_ml_utils_torch/loss/classificaion.py
pandas_ml_utils_torch/loss/probabilistic.py
pandas_ml_utils_torch/loss/simple_losses.py
pandas_ml_utils_torch/loss/soft_dtw.py
pandas_ml_utils_torch/loss/__pycache__/__init__.cpython-37.pyc
pandas_ml_utils_torch/loss/__pycache__/__init__.cpython-38.pyc
pandas_ml_utils_torch/loss/__pycache__/_loss_utils.cpython-38.pyc
pandas_ml_utils_torch/loss/__pycache__/classificaion.cpython-37.pyc
pandas_ml_utils_torch/loss/__pycache__/classificaion.cpython-38.pyc
pandas_ml_utils_torch/loss/__pycache__/probabilistic.cpython-37.pyc
pandas_ml_utils_torch/loss/__pycache__/probabilistic.cpython-38.pyc
pandas_ml_utils_torch/loss/__pycache__/simple_losses.cpython-37.pyc
